{"state":
 [{"n":0,
   "id":["kleene-main",["101",0]],
   "trans":[{"to":1,"in":"1"}]},
  {"n":1,
   "id":["kleene-main",["101",1]],
   "trans":[{"to":2,"in":"0"}]},
  {"n":2,
   "id":["kleene-main",["101",2]],
   "trans":[{"to":3,"in":"1"}]},
  {"n":3,
   "id":["kleene-main",["101",3]],
   "trans":[{"to":4},
            {"to":8}]},
  {"n":4,
   "id":["kleene-loop",["001",0]],
   "trans":[{"to":5,"in":"0"}]},
  {"n":5,
   "id":["kleene-loop",["001",1]],
   "trans":[{"to":6,"in":"0"}]},
  {"n":6,
   "id":["kleene-loop",["001",2]],
   "trans":[{"to":7,"in":"1"}]},
  {"n":7,
   "id":["kleene-loop",["001",3]],
   "trans":[{"to":0}]},
  {"n":8}
 ]
}
